mapbot_frontend/__init__.py
mapbot_frontend/frontend/build/asset-manifest.json
mapbot_frontend/frontend/build/bootstrap.min.css
mapbot_frontend/frontend/build/index.html
mapbot_frontend/frontend/build/static/css/2.19230d7e.chunk.css
mapbot_frontend/frontend/build/static/css/2.19230d7e.chunk.css.map
mapbot_frontend/frontend/build/static/js/2.be748679.chunk.js
mapbot_frontend/frontend/build/static/js/2.be748679.chunk.js.LICENSE.txt
mapbot_frontend/frontend/build/static/js/2.be748679.chunk.js.map
mapbot_frontend/frontend/build/static/js/main.84debba5.chunk.js
mapbot_frontend/frontend/build/static/js/main.84debba5.chunk.js.map
mapbot_frontend/frontend/build/static/js/runtime-main.48f3c07e.js
mapbot_frontend/frontend/build/static/js/runtime-main.48f3c07e.js.map
mapbot_frontend-0.1.24.dist-info/METADATA
mapbot_frontend-0.1.24.dist-info/WHEEL
mapbot_frontend-0.1.24.dist-info/top_level.txt
mapbot_frontend-0.1.24.dist-info/RECORD
