Metadata-Version: 2.1
Name: mapbot_frontend
Version: 0.1.24
Summary: A frontend package for MapBot
Home-page: UNKNOWN
Author: Martin Weiss
License: UNKNOWN
Platform: UNKNOWN
Classifier: Programming Language :: Python :: 3
Classifier: License :: OSI Approved :: MIT License
Classifier: Operating System :: OS Independent
